rpi_power_meter_mqtt/__init__.py
rpi_power_meter_mqtt/logger.py
rpi_power_meter_mqtt-0.0.1.data/scripts/rpi-power-meter-mqtt
rpi_power_meter_mqtt-0.0.1.dist-info/DESCRIPTION.rst
rpi_power_meter_mqtt-0.0.1.dist-info/METADATA
rpi_power_meter_mqtt-0.0.1.dist-info/RECORD
rpi_power_meter_mqtt-0.0.1.dist-info/WHEEL
rpi_power_meter_mqtt-0.0.1.dist-info/metadata.json
rpi_power_meter_mqtt-0.0.1.dist-info/top_level.txt
