Metadata-Version: 2.0
Name: rpi-power-meter-mqtt
Version: 0.0.1
Summary: Send current power consumption of a power meters to mqtt broker
Home-page: https://github.com/goodfield/rpi-power-meter-mqtt.git
Author: David Uebelacker
Author-email: david@uebelacker.ch
License: The MIT License (MIT)
Requires-Dist: paho-mqtt
